py_orchestrator/__init__.py
py_orchestrator/pipeline.py
py_orchestrator/stage.py
py_orchestrator-0.0.3.dist-info/LICENSE
py_orchestrator-0.0.3.dist-info/METADATA
py_orchestrator-0.0.3.dist-info/WHEEL
py_orchestrator-0.0.3.dist-info/top_level.txt
py_orchestrator-0.0.3.dist-info/RECORD
