Metadata-Version: 2.1
Name: py-orchestrator
Version: 0.0.3
Summary: Orchestrator for running python pipelines
Home-page: https://github.com/abhinav-kumar-thakur/orchestrator
Author: Abhinav Kumar Thakur
Author-email: 
License: UNKNOWN
Project-URL: Bug Tracker, https://github.com/abhinav-kumar-thakur/orchestrator/issues
Platform: UNKNOWN
Classifier: Programming Language :: Python :: 3
Classifier: License :: OSI Approved :: MIT License
Classifier: Operating System :: OS Independent
Requires-Python: >=3.6
